cyclist/__init__.py
cyclist/cycle_events.py
cyclist-0.0.8.dist-info/LICENCE
cyclist-0.0.8.dist-info/METADATA
cyclist-0.0.8.dist-info/WHEEL
cyclist-0.0.8.dist-info/top_level.txt
cyclist-0.0.8.dist-info/RECORD
