Metadata-Version: 2.1
Name: cyclist
Version: 0.0.8
Summary: Cycle-based data analysis toolbox
Home-page: https://github.com/MortimerMcMire/cyclist
Author: Ben Andrews
Author-email: mortimermcmiresa@gmail.com
License: UNKNOWN
Platform: UNKNOWN
Classifier: Programming Language :: Python :: 3
Classifier: License :: OSI Approved :: MIT License
Classifier: Operating System :: OS Independent
Requires-Dist: pandas (>=0.11.0)
